{
    "LV cable RH side": [
        {
            "assemblyFilePath": "ABC099001_03_01",
            "model-state": "TYPE 2 - LV CABLE RH SIDE",
            "representations": "TYPE 2 - LV CABLE RH SIDE"
        },
        {
            "assemblyFilePath": "ABC099001_01_01",
            "model-state": "TYPE 2 - LV CABLE RH SIDE",
            "representations": "TYPE 2 - LV CABLE RH SIDE"
        }
    ],
    "LV cable LV side": [
        {
            "assemblyFilePath": "ABC099001_03_01",
            "model-state": "TYPE 1 - LV CABLE LV SIDE",
            "representations": "TYPE 1 - LV CABLE LV SIDE"
        },
        {
            "assemblyFilePath": "ABC099001_01_01",
            "model-state": "TYPE 1 - LV CABLE LV SIDE",
            "representations": "TYPE 1 - LV CABLE LV SIDE"
        }
    ]
}